django_dharma/__init__.py
django_dharma/base.py
django_dharma/collector.py
django_dharma/management/__init__.py
django_dharma/management/commands/__init__.py
django_dharma/management/commands/perform_checks.py
django_dharma/migrations/0001_initial.py
django_dharma/migrations/__init__.py
django_dharma/models.py
django_dharma/protocols.py
django_dharma/tests/__init__.py
django_dharma/tests/test_anomalies.py
django_dharma/tests/test_collector.py
django_dharma/tests/test_protocols.py
django_dharma-0.1.0.dist-info/METADATA
django_dharma-0.1.0.dist-info/WHEEL
django_dharma-0.1.0.dist-info/RECORD
