Metadata-Version: 2.1
Name: django-dharma
Version: 0.1.0
Summary: A Django app to run checks on models
Author: Ivan Tabarelli
Author-email: itabarelli@gmail.com
Requires-Python: >=3.9,<4.0
Classifier: Programming Language :: Python :: 3
Classifier: Programming Language :: Python :: 3.9
Classifier: Programming Language :: Python :: 3.10
Classifier: Programming Language :: Python :: 3.11
Classifier: Programming Language :: Python :: 3.12
Requires-Dist: Django (>=4.2,<5.0)
Project-URL: homepage, https://github.com/yourusername/django-dharma
